{
  "_comment": "Keys are '{league}-{espn_event_id}'. Auto-populated by scrape-streams.ts.",
  "_date": "2026-05-07",
  "mlb-401815248": [
    {
      "label": "HD 1",
      "url": "https://embedsports.top/embed/admin/ppv-texas-rangers-vs-new-york-yankees/1",
      "quality": "HD",
      "language": "English - Rangers Sports Network"
    },
    {
      "label": "HD 2",
      "url": "https://embedsports.top/embed/delta/live_mlb_yankees-rangers-live-streaming-1266861870/1",
      "quality": "HD",
      "language": "English"
    },
    {
      "label": "HD 3",
      "url": "https://embedsports.top/embed/echo/new-york-yankees-vs-texas-rangers-baseball-178566/1",
      "quality": "HD",
      "language": "EN"
    },
    {
      "label": "HD 4",
      "url": "https://embedsports.top/embed/golf/22210/1",
      "quality": "HD",
      "language": "English"
    }
  ],
  "mlb-401815246": [
    {
      "label": "HD 1",
      "url": "https://embedsports.top/embed/admin/ppv-minnesota-twins-vs-washington-nationals/1",
      "quality": "HD",
      "language": "English - Nationals.TV"
    },
    {
      "label": "HD 2",
      "url": "https://embedsports.top/embed/delta/live_mlb_nationals-twins-live-streaming-1266862869/1",
      "quality": "HD",
      "language": "English"
    },
    {
      "label": "HD 3",
      "url": "https://embedsports.top/embed/delta/live_mlb_nationals-twins-live-streaming-1266862869/2",
      "quality": "HD",
      "language": "English"
    },
    {
      "label": "HD 4",
      "url": "https://embedsports.top/embed/echo/washington-nationals-vs-minnesota-twins-baseball-178569/1",
      "quality": "HD",
      "language": "EN"
    },
    {
      "label": "HD 5",
      "url": "https://embedsports.top/embed/echo/washington-nationals-vs-minnesota-twins-baseball-178569/2",
      "quality": "HD",
      "language": "EN"
    },
    {
      "label": "HD 6",
      "url": "https://embedsports.top/embed/golf/22211/1",
      "quality": "HD",
      "language": "English"
    }
  ],
  "mlb-401815250": [
    {
      "label": "HD 1",
      "url": "https://embedsports.top/embed/admin/ppv-cleveland-guardians-vs-kansas-city-royals/1",
      "quality": "HD",
      "language": "English - Royals.TV"
    },
    {
      "label": "HD 2",
      "url": "https://embedsports.top/embed/delta/live_mlb_royals-guardians-live-streaming-1266863868/1",
      "quality": "HD",
      "language": "English"
    },
    {
      "label": "HD 3",
      "url": "https://embedsports.top/embed/delta/live_mlb_royals-guardians-live-streaming-1266863868/2",
      "quality": "HD",
      "language": "English"
    },
    {
      "label": "HD 4",
      "url": "https://embedsports.top/embed/echo/kansas-city-royals-vs-cleveland-guardians-baseball-178572/1",
      "quality": "HD",
      "language": "EN"
    },
    {
      "label": "HD 5",
      "url": "https://embedsports.top/embed/echo/kansas-city-royals-vs-cleveland-guardians-baseball-178572/2",
      "quality": "HD",
      "language": "EN"
    },
    {
      "label": "HD 6",
      "url": "https://embedsports.top/embed/golf/22212/1",
      "quality": "HD",
      "language": "English"
    }
  ],
  "mlb-401815249": [
    {
      "label": "HD 1",
      "url": "https://embedsports.top/embed/admin/ppv-cincinnati-reds-vs-chicago-cubs/1",
      "quality": "HD",
      "language": "English - Marquee Sports Net"
    },
    {
      "label": "HD 2",
      "url": "https://embedsports.top/embed/delta/live_mlb_cubs-reds-live-streaming-1266864867/1",
      "quality": "HD",
      "language": "English"
    },
    {
      "label": "HD 3",
      "url": "https://embedsports.top/embed/delta/live_mlb_cubs-reds-live-streaming-1266864867/2",
      "quality": "HD",
      "language": "English"
    },
    {
      "label": "HD 4",
      "url": "https://embedsports.top/embed/echo/chicago-cubs-vs-cincinnati-reds-baseball-178573/1",
      "quality": "HD",
      "language": "EN"
    },
    {
      "label": "HD 5",
      "url": "https://embedsports.top/embed/echo/chicago-cubs-vs-cincinnati-reds-baseball-178573/2",
      "quality": "HD",
      "language": "EN"
    },
    {
      "label": "HD 6",
      "url": "https://embedsports.top/embed/golf/22213/1",
      "quality": "HD",
      "language": "English"
    }
  ],
  "mlb-401871498": [
    {
      "label": "HD 1",
      "url": "https://embedsports.top/embed/admin/ppv-new-york-mets-vs-colorado-rockies/1",
      "quality": "HD",
      "language": "English - Rockies.TV"
    },
    {
      "label": "HD 2",
      "url": "https://embedsports.top/embed/delta/live_mlb_rockies-mets-live-streaming-1301135562/1",
      "quality": "HD",
      "language": "English"
    },
    {
      "label": "HD 3",
      "url": "https://embedsports.top/embed/delta/live_mlb_rockies-mets-live-streaming-1301135562/2",
      "quality": "HD",
      "language": "English"
    },
    {
      "label": "HD 4",
      "url": "https://embedsports.top/embed/echo/colorado-rockies-vs-new-york-mets-baseball-178547/1",
      "quality": "HD",
      "language": "EN"
    },
    {
      "label": "HD 5",
      "url": "https://embedsports.top/embed/echo/colorado-rockies-vs-new-york-mets-baseball-178547/2",
      "quality": "HD",
      "language": "EN"
    },
    {
      "label": "HD 6",
      "url": "https://embedsports.top/embed/golf/22214/1",
      "quality": "HD",
      "language": "English"
    }
  ],
  "mlb-401815251": [
    {
      "label": "HD 1",
      "url": "https://embedsports.top/embed/admin/ppv-pittsburgh-pirates-vs-arizona-diamondbacks/1",
      "quality": "HD",
      "language": "English - DBACKS.TV"
    },
    {
      "label": "HD 2",
      "url": "https://embedsports.top/embed/delta/live_mlb_diamondbacks-pirates-live-streaming-1266865866/1",
      "quality": "HD",
      "language": "English"
    },
    {
      "label": "HD 3",
      "url": "https://embedsports.top/embed/echo/arizona-diamondbacks-vs-pittsburgh-pirates-baseball-178571/1",
      "quality": "HD",
      "language": "EN"
    },
    {
      "label": "HD 4",
      "url": "https://embedsports.top/embed/echo/arizona-diamondbacks-vs-pittsburgh-pirates-baseball-178571/2",
      "quality": "HD",
      "language": "EN"
    },
    {
      "label": "HD 5",
      "url": "https://embedsports.top/embed/golf/22215/1",
      "quality": "HD",
      "language": "English"
    }
  ],
  "mlb-401815244": [
    {
      "label": "HD 1",
      "url": "https://embedsports.top/embed/admin/ppv-athletics-vs-philadelphia-phillies/1",
      "quality": "HD",
      "language": "English - NBC Sports Phil"
    },
    {
      "label": "HD 2",
      "url": "https://embedsports.top/embed/delta/live_mlb_phillies-athletics-live-streaming-1266867864/1",
      "quality": "HD",
      "language": "English"
    },
    {
      "label": "HD 3",
      "url": "https://embedsports.top/embed/echo/philadelphia-phillies-vs-athletics-baseball-178568/1",
      "quality": "HD",
      "language": "EN"
    },
    {
      "label": "HD 4",
      "url": "https://embedsports.top/embed/echo/philadelphia-phillies-vs-athletics-baseball-178568/2",
      "quality": "HD",
      "language": "EN"
    },
    {
      "label": "HD 5",
      "url": "https://embedsports.top/embed/golf/22216/1",
      "quality": "HD",
      "language": "English"
    }
  ],
  "mlb-401815245": [
    {
      "label": "HD 1",
      "url": "https://embedsports.top/embed/admin/ppv-baltimore-orioles-vs-miami-marlins/1",
      "quality": "HD",
      "language": "English - Marlins.TV"
    },
    {
      "label": "HD 2",
      "url": "https://embedsports.top/embed/delta/live_mlb_marlins-orioles-live-streaming-1266866865/1",
      "quality": "HD",
      "language": "English"
    },
    {
      "label": "HD 3",
      "url": "https://embedsports.top/embed/delta/live_mlb_marlins-orioles-live-streaming-1266866865/2",
      "quality": "HD",
      "language": "English"
    },
    {
      "label": "HD 4",
      "url": "https://embedsports.top/embed/echo/miami-marlins-vs-baltimore-orioles-baseball-178570/1",
      "quality": "HD",
      "language": "EN"
    },
    {
      "label": "HD 5",
      "url": "https://embedsports.top/embed/echo/miami-marlins-vs-baltimore-orioles-baseball-178570/2",
      "quality": "HD",
      "language": "EN"
    },
    {
      "label": "HD 6",
      "url": "https://embedsports.top/embed/golf/22217/1",
      "quality": "HD",
      "language": "English"
    }
  ],
  "nba-401871334": [
    {
      "label": "HD 1",
      "url": "https://embedsports.top/embed/admin/ppv-cleveland-cavaliers-vs-detroit-pistons/1",
      "quality": "HD",
      "language": "English - Prime Video"
    },
    {
      "label": "HD 2",
      "url": "https://embedsports.top/embed/delta/live_nba_pistons-cavaliers-live-streaming-1300199499/1",
      "quality": "HD",
      "language": "English"
    },
    {
      "label": "HD 3",
      "url": "https://embedsports.top/embed/echo/detroit-pistons-vs-cleveland-cavaliers-basketball-498883/1",
      "quality": "HD",
      "language": "EN"
    },
    {
      "label": "HD 4",
      "url": "https://embedsports.top/embed/echo/detroit-pistons-vs-cleveland-cavaliers-basketball-498883/2",
      "quality": "HD",
      "language": "EN"
    },
    {
      "label": "HD 5",
      "url": "https://embedsports.top/embed/echo/detroit-pistons-vs-cleveland-cavaliers-basketball-498883/3",
      "quality": "HD",
      "language": "EN"
    },
    {
      "label": "HD 6",
      "url": "https://embedsports.top/embed/golf/22206/1",
      "quality": "HD",
      "language": "English"
    }
  ],
  "mlb-401815247": [
    {
      "label": "HD 1",
      "url": "https://embedsports.top/embed/admin/ppv-tampa-bay-rays-vs-boston-red-sox/1",
      "quality": "HD",
      "language": "English - ESPN"
    },
    {
      "label": "HD 2",
      "url": "https://embedsports.top/embed/delta/live_mlb_red-sox-rays-live-streaming-1266868863/1",
      "quality": "HD",
      "language": "English"
    },
    {
      "label": "HD 3",
      "url": "https://embedsports.top/embed/delta/live_mlb_red-sox-rays-live-streaming-1266868863/2",
      "quality": "HD",
      "language": "English"
    },
    {
      "label": "HD 4",
      "url": "https://embedsports.top/embed/echo/boston-red-sox-vs-tampa-bay-rays-baseball-178574/1",
      "quality": "HD",
      "language": "EN"
    },
    {
      "label": "HD 5",
      "url": "https://embedsports.top/embed/echo/boston-red-sox-vs-tampa-bay-rays-baseball-178574/2",
      "quality": "HD",
      "language": "EN"
    },
    {
      "label": "HD 6",
      "url": "https://embedsports.top/embed/golf/22218/1",
      "quality": "HD",
      "language": "English"
    }
  ],
  "nba-401871327": [
    {
      "label": "HD 1",
      "url": "https://embedsports.top/embed/admin/ppv-los-angeles-lakers-vs-oklahoma-city-thunder/1",
      "quality": "HD",
      "language": "English - Prime Video"
    },
    {
      "label": "HD 2",
      "url": "https://embedsports.top/embed/delta/live_nba_thunder-lakers-live-streaming-1295647056/1",
      "quality": "HD",
      "language": "English"
    },
    {
      "label": "HD 3",
      "url": "https://embedsports.top/embed/echo/oklahoma-city-thunder-vs-los-angeles-lakers-basketball-498799/1",
      "quality": "HD",
      "language": "EN"
    },
    {
      "label": "HD 4",
      "url": "https://embedsports.top/embed/echo/oklahoma-city-thunder-vs-los-angeles-lakers-basketball-498799/2",
      "quality": "HD",
      "language": "EN"
    },
    {
      "label": "HD 5",
      "url": "https://embedsports.top/embed/echo/oklahoma-city-thunder-vs-los-angeles-lakers-basketball-498799/3",
      "quality": "HD",
      "language": "EN"
    },
    {
      "label": "HD 6",
      "url": "https://embedsports.top/embed/golf/22207/1",
      "quality": "HD",
      "language": "English"
    }
  ]
}