{
  "_comment": "Keys are '{league}-{espn_event_id}'. Auto-populated by scrape-streams.ts.",
  "_date": "2026-04-18",
  "nba-401869187": [
    {
      "label": "HD 1",
      "url": "https://embedsports.top/embed/admin/ppv-toronto-raptors-vs-cleveland-cavaliers/1",
      "quality": "HD",
      "language": "English"
    },
    {
      "label": "HD 2",
      "url": "https://embedsports.top/embed/admin/ppv-toronto-raptors-vs-cleveland-cavaliers/2",
      "quality": "HD",
      "language": "English"
    },
    {
      "label": "HD 3",
      "url": "https://embedsports.top/embed/delta/live_nba_cavaliers-raptors-live-streaming-1269750978/1",
      "quality": "HD",
      "language": "English"
    },
    {
      "label": "HD 4",
      "url": "https://embedsports.top/embed/echo/cleveland-cavaliers-vs-toronto-raptors-basketball-497764/1",
      "quality": "HD",
      "language": "EN"
    },
    {
      "label": "HD 5",
      "url": "https://embedsports.top/embed/echo/cleveland-cavaliers-vs-toronto-raptors-basketball-497764/2",
      "quality": "HD",
      "language": "EN"
    },
    {
      "label": "HD 6",
      "url": "https://embedsports.top/embed/golf/21706/1",
      "quality": "HD",
      "language": "English"
    },
    {
      "label": "HD 7",
      "url": "https://embedsports.top/embed/delta/live_nba_cavaliers-raptors-live-streaming-1269750978/2",
      "quality": "HD",
      "language": "English"
    }
  ],
  "mlb-401814989": [
    {
      "label": "HD 1",
      "url": "https://embedsports.top/embed/admin/ppv-kansas-city-royals-vs-new-york-yankees/1",
      "quality": "HD",
      "language": "English"
    },
    {
      "label": "HD 2",
      "url": "https://embedsports.top/embed/admin/ppv-kansas-city-royals-vs-new-york-yankees/2",
      "quality": "HD",
      "language": "English"
    },
    {
      "label": "HD 3",
      "url": "https://embedsports.top/embed/delta/live_mlb_yankees-royals-live-streaming-1200326472/1",
      "quality": "HD",
      "language": "English"
    },
    {
      "label": "HD 4",
      "url": "https://embedsports.top/embed/delta/live_mlb_yankees-royals-live-streaming-1200326472/2",
      "quality": "HD",
      "language": "English"
    },
    {
      "label": "HD 5",
      "url": "https://embedsports.top/embed/echo/new-york-yankees-vs-kansas-city-royals-baseball-178313/1",
      "quality": "HD",
      "language": "EN"
    },
    {
      "label": "HD 6",
      "url": "https://embedsports.top/embed/echo/new-york-yankees-vs-kansas-city-royals-baseball-178313/2",
      "quality": "HD",
      "language": "EN"
    },
    {
      "label": "HD 7",
      "url": "https://embedsports.top/embed/golf/21725/1",
      "quality": "HD",
      "language": "English"
    }
  ],
  "mlb-401814993": [
    {
      "label": "HD 1",
      "url": "https://embedsports.top/embed/admin/ppv-cincinnati-reds-vs-minnesota-twins/1",
      "quality": "HD",
      "language": "English"
    },
    {
      "label": "HD 2",
      "url": "https://embedsports.top/embed/admin/ppv-cincinnati-reds-vs-minnesota-twins/2",
      "quality": "HD",
      "language": "English"
    },
    {
      "label": "HD 3",
      "url": "https://embedsports.top/embed/delta/live_mlb_twins-reds-live-streaming-1200327471/1",
      "quality": "HD",
      "language": "English"
    },
    {
      "label": "HD 4",
      "url": "https://embedsports.top/embed/delta/live_mlb_twins-reds-live-streaming-1200327471/2",
      "quality": "HD",
      "language": "English"
    },
    {
      "label": "HD 5",
      "url": "https://embedsports.top/embed/echo/minnesota-twins-vs-cincinnati-reds-baseball-178314/1",
      "quality": "HD",
      "language": "EN"
    },
    {
      "label": "HD 6",
      "url": "https://embedsports.top/embed/echo/minnesota-twins-vs-cincinnati-reds-baseball-178314/2",
      "quality": "HD",
      "language": "EN"
    },
    {
      "label": "HD 7",
      "url": "https://embedsports.top/embed/golf/21726/1",
      "quality": "HD",
      "language": "English"
    }
  ],
  "mlb-401814994": [
    {
      "label": "HD 1",
      "url": "https://embedsports.top/embed/admin/ppv-new-york-mets-vs-chicago-cubs/1",
      "quality": "HD",
      "language": "English"
    },
    {
      "label": "HD 2",
      "url": "https://embedsports.top/embed/admin/ppv-new-york-mets-vs-chicago-cubs/2",
      "quality": "HD",
      "language": "English"
    },
    {
      "label": "HD 3",
      "url": "https://embedsports.top/embed/delta/live_mlb_cubs-mets-live-streaming-1200328470/1",
      "quality": "HD",
      "language": "English"
    },
    {
      "label": "HD 4",
      "url": "https://embedsports.top/embed/delta/live_mlb_cubs-mets-live-streaming-1200328470/2",
      "quality": "HD",
      "language": "English"
    },
    {
      "label": "HD 5",
      "url": "https://embedsports.top/embed/echo/chicago-cubs-vs-new-york-mets-baseball-178319/1",
      "quality": "HD",
      "language": "EN"
    },
    {
      "label": "HD 6",
      "url": "https://embedsports.top/embed/echo/chicago-cubs-vs-new-york-mets-baseball-178319/2",
      "quality": "HD",
      "language": "EN"
    },
    {
      "label": "HD 7",
      "url": "https://embedsports.top/embed/golf/21727/1",
      "quality": "HD",
      "language": "English"
    }
  ],
  "nba-401869188": [
    {
      "label": "HD 1",
      "url": "https://embedsports.top/embed/admin/ppv-minnesota-timberwolves-vs-denver-nuggets/1",
      "quality": "HD",
      "language": "English"
    },
    {
      "label": "HD 2",
      "url": "https://embedsports.top/embed/admin/ppv-minnesota-timberwolves-vs-denver-nuggets/2",
      "quality": "HD",
      "language": "English"
    },
    {
      "label": "HD 3",
      "url": "https://embedsports.top/embed/delta/live_nba_nuggets-timberwolves-live-streaming-1269952776/1",
      "quality": "HD",
      "language": "English"
    },
    {
      "label": "HD 4",
      "url": "https://embedsports.top/embed/delta/live_nba_nuggets-timberwolves-live-streaming-1269952776/2",
      "quality": "HD",
      "language": "English"
    },
    {
      "label": "HD 5",
      "url": "https://embedsports.top/embed/echo/denver-nuggets-vs-minnesota-timberwolves-basketball-497765/1",
      "quality": "HD",
      "language": "EN"
    },
    {
      "label": "HD 6",
      "url": "https://embedsports.top/embed/echo/denver-nuggets-vs-minnesota-timberwolves-basketball-497765/2",
      "quality": "HD",
      "language": "EN"
    },
    {
      "label": "HD 7",
      "url": "https://embedsports.top/embed/golf/21707/1",
      "quality": "HD",
      "language": "English"
    }
  ],
  "mlb-401814992": [
    {
      "label": "HD 1",
      "url": "https://embedsports.top/embed/admin/ppv-tampa-bay-rays-vs-pittsburgh-pirates/1",
      "quality": "HD",
      "language": "English"
    },
    {
      "label": "HD 2",
      "url": "https://embedsports.top/embed/admin/ppv-tampa-bay-rays-vs-pittsburgh-pirates/2",
      "quality": "HD",
      "language": "English"
    },
    {
      "label": "HD 3",
      "url": "https://embedsports.top/embed/delta/live_mlb_pirates-rays-live-streaming-1200330468/1",
      "quality": "HD",
      "language": "English"
    },
    {
      "label": "HD 4",
      "url": "https://embedsports.top/embed/delta/live_mlb_pirates-rays-live-streaming-1200330468/2",
      "quality": "HD",
      "language": "English"
    },
    {
      "label": "HD 5",
      "url": "https://embedsports.top/embed/echo/pittsburgh-pirates-vs-tampa-bay-rays-baseball-178311/1",
      "quality": "HD",
      "language": "EN"
    },
    {
      "label": "HD 6",
      "url": "https://embedsports.top/embed/echo/pittsburgh-pirates-vs-tampa-bay-rays-baseball-178311/2",
      "quality": "HD",
      "language": "EN"
    },
    {
      "label": "HD 7",
      "url": "https://embedsports.top/embed/golf/21729/1",
      "quality": "HD",
      "language": "English"
    }
  ]
}